[
    {"date": "2022-01-04", "china": 8.23, "eu": 96.42, "south_korea": 26.16, "us_california": 33},
    {"date": "2022-01-05", "china": 8.18, "eu": 99.43, "south_korea": 26.16, "us_california": 33},
    {"date": "2022-01-06", "china": 8.22, "eu": 98.10, "south_korea": 26.16, "us_california": 34.35},
    {"date": "2022-01-07", "china": 8.27, "eu": 96.94, "south_korea": 26.16, "us_california": 34.35},
    {"date": "2022-01-10", "china": 8.37, "eu": 92.03, "south_korea": 26.16, "us_california": 34.35},
    {"date": "2022-01-11", "china": 8.26, "eu": 93.11, "south_korea": 26.16, "us_california": 34.35},
    {"date": "2022-01-12", "china": 8.33, "eu": 91.96, "south_korea": 26.16, "us_california": 34.35},
    {"date": "2022-01-13", "china": 8.29, "eu": 92.66, "south_korea": 26.16, "us_california": 31.7},
    {"date": "2022-01-14", "china": 8.29, "eu": 93.98, "south_korea": 26.16, "us_california": 31.7},
    {"date": "2022-01-17", "china": 8.40, "eu": 84.42, "south_korea": 26.16, "us_california": 31.7},
    {"date": "2022-01-18", "china": 8.40, "eu": 93.32, "south_korea": 26.16, "us_california": 31.7},
    {"date": "2022-01-19", "china": 8.04, "eu": 93.02, "south_korea": 26.16, "us_california": 31.7},
    {"date": "2022-01-20", "china": 8.33, "eu": 96.92, "south_korea": 26.16, "us_california": 31.35},
    {"date": "2022-01-21", "china": 8.25, "eu": 96.00, "south_korea": 26.16, "us_california": 31.35},
    {"date": "2022-01-24", "china": 8.31, "eu": 94.39, "south_korea": 26.16, "us_california": 31.35},
    {"date": "2022-01-25", "china": 8.30, "eu": 98.20, "south_korea": 26.16, "us_california": 31.35},
    {"date": "2022-01-26", "china": 8.31, "eu": 99.99, "south_korea": 26.16, "us_california": 31.35},
    {"date": "2022-01-27", "china": 8.04, "eu": 100.04, "south_korea": 26.16, "us_california": 29.5},
    {"date": "2022-01-28", "china": 8.81, "eu": 99.25, "south_korea": 26.16, "us_california": 29.5},
    {"date": "2022-01-31", "china": 8.81, "eu": 99.83, "south_korea": 26.16, "us_california": 29.5},
    {"date": "2022-02-01", "china": 8.81, "eu": 100.66, "south_korea": 26.16, "us_california": 29.5},
    {"date": "2022-02-02", "china": 8.81, "eu": 106.28, "south_korea": 26.16, "us_california": 29.5},
    {"date": "2022-02-03", "china": 8.81, "eu": 108.24, "south_korea": 26.16, "us_california": 29.95},
    {"date": "2022-02-04", "china": 8.81, "eu": 109.88, "south_korea": 26.16, "us_california": 29.95},
    {"date": "2022-02-07", "china": 8.34, "eu": 110.21, "south_korea": 26.16, "us_california": 29.95},
    {"date": "2022-02-08", "china": 8.40, "eu": 109.56, "south_korea": 26.16, "us_california": 29.95},
    {"date": "2022-02-09", "china": 8.40, "eu": 105.10, "south_korea": 26.16, "us_california": 29.95},
    {"date": "2022-02-10", "china": 8.61, "eu": 105.04, "south_korea": 26.16, "us_california": 28.95},
    {"date": "2022-02-11", "china": 8.06, "eu": 105.97, "south_korea": 26.16, "us_california": 28.95},
    {"date": "2022-02-14", "china": 8.39, "eu": 103.51, "south_korea": 26.16, "us_california": 28.95},
    {"date": "2022-02-15", "china": 8.39, "eu": 102.65, "south_korea": 26.16, "us_california": 28.95},
    {"date": "2022-02-16", "china": 8.13, "eu": 102.31, "south_korea": 26.16, "us_california": 28.95},
    {"date": "2022-02-17", "china": 8.11, "eu": 98.22, "south_korea": 26.16, "us_california": 28.8},
    {"date": "2022-02-18", "china": 8.17, "eu": 101.22, "south_korea": 26.16, "us_california": 28.8},
    {"date": "2022-02-21", "china": 8.18, "eu": 101.69, "south_korea": 26.16, "us_california": 28.8},
    {"date": "2022-02-22", "china": 8.15, "eu": 101.68, "south_korea": 26.16, "us_california": 28.8},
    {"date": "2022-02-23", "china": 8.11, "eu": 107.58, "south_korea": 26.16, "us_california": 28.8},
    {"date": "2022-02-24", "china": 8.33, "eu": 97.27, "south_korea": 26.16, "us_california": 28.75},
    {"date": "2022-02-25", "china": 8.40, "eu": 98.91, "south_korea": 26.16, "us_california": 28.75},
    {"date": "2022-02-28", "china": 8.29, "eu": 93.10, "south_korea": 26.16, "us_california": 28.75},
    {"date": "2022-03-01", "china": 8.30, "eu": 77.14, "south_korea": 26.16, "us_california": 28.75},
    {"date": "2022-03-02", "china": 8.31, "eu": 75.15, "south_korea": 26.16, "us_california": 28.75},
    {"date": "2022-03-03", "china": 8.31, "eu": 74.33, "south_korea": 26.16, "us_california": 27.85},
    {"date": "2022-03-04", "china": 8.31, "eu": 71.56, "south_korea": 26.16, "us_california": 27.85},
    {"date": "2022-03-07", "china": 8.19, "eu": 63.20, "south_korea": 23.76, "us_california": 27.85},
    {"date": "2022-03-08", "china": 8.18, "eu": 74.31, "south_korea": 23.76, "us_california": 27.85},
    {"date": "2022-03-09", "china": 8.33, "eu": 80.75, "south_korea": 23.76, "us_california": 27.85},
    {"date": "2022-03-10", "china": 8.22, "eu": 83.06, "south_korea": 24.00, "us_california": 27.25},
    {"date": "2022-03-11", "china": 8.27, "eu": 83.80, "south_korea": 21.44, "us_california": 27.25},
    {"date": "2022-03-14", "china": 8.33, "eu": 85.98, "south_korea": 21.44, "us_california": 27.25},
    {"date": "2022-03-15", "china": 8.29, "eu": 84.81, "south_korea": 21.44, "us_california": 27.25},
    {"date": "2022-03-16", "china": 8.18, "eu": 86.27, "south_korea": 21.60, "us_california": 27.25},
    {"date": "2022-03-17", "china": 8.18, "eu": 88.76, "south_korea": 21.60, "us_california": 28.35},
    {"date": "2022-03-18", "china": 8.33, "eu": 87.19, "south_korea": 18.96, "us_california": 28.35},
    {"date": "2022-03-21", "china": 8.40, "eu": 86.82, "south_korea": 17.08, "us_california": 28.35},
    {"date": "2022-03-22", "china": 8.33, "eu": 88.64, "south_korea": 15.40, "us_california": 28.35},
    {"date": "2022-03-23", "china": 8.39, "eu": 84.11, "south_korea": 15.40, "us_california": 28.35},
    {"date": "2022-03-24", "china": 8.33, "eu": 86.29, "south_korea": 15.40, "us_california": 28.08},
    {"date": "2022-03-25", "china": 8.33, "eu": 86.38, "south_korea": 18.16, "us_california": 28.08},
    {"date": "2022-03-28", "china": 8.33, "eu": 88.44, "south_korea": 18.16, "us_california": 28.08},
    {"date": "2022-03-29", "china": 8.40, "eu": 90.54, "south_korea": 18.16, "us_california": 28.08},
    {"date": "2022-03-30", "china": 8.40, "eu": 87.50, "south_korea": 18.16, "us_california": 28.08},
    {"date": "2022-03-31", "china": 8.41, "eu": 85.59, "south_korea": 18.16, "us_california": 31.1},
    {"date": "2022-04-01", "china": 8.40, "eu": 86.64, "south_korea": 18.16, "us_california": 31.1},
    {"date": "2022-04-04", "china": 8.40, "eu": 86.29, "south_korea": 18.16, "us_california": 31.1},
    {"date": "2022-04-05", "china": 8.40, "eu": 85.65, "south_korea": 18.16, "us_california": 31.1},
    {"date": "2022-04-06", "china": 8.61, "eu": 84.20, "south_korea": 18.16, "us_california": 31.1},
    {"date": "2022-04-07", "china": 8.47, "eu": 87.19, "south_korea": 18.16, "us_california": 31.9},
    {"date": "2022-04-08", "china": 8.61, "eu": 87.08, "south_korea": 18.16, "us_california": 31.9},
    {"date": "2022-04-11", "china": 8.61, "eu": 84.66, "south_korea": 18.16, "us_california": 31.9},
    {"date": "2022-04-12", "china": 8.61, "eu": 85.79, "south_korea": 18.16, "us_california": 31.9},
    {"date": "2022-04-13", "china": 8.61, "eu": 84.25, "south_korea": 18.16, "us_california": 31.9},
    {"date": "2022-04-14", "china": 8.61, "eu": 86.36, "south_korea": 18.16, "us_california": 32},
    {"date": "2022-04-18", "china": 8.61, "eu": 86.36, "south_korea": 18.16, "us_california": 32},
    {"date": "2022-04-19", "china": 8.61, "eu": 86.53, "south_korea": 18.16, "us_california": 32},
    {"date": "2022-04-20", "china": 8.61, "eu": 94.42, "south_korea": 18.16, "us_california": 32},
    {"date": "2022-04-21", "china": 8.61, "eu": 93.95, "south_korea": 18.16, "us_california": 32.75},
    {"date": "2022-04-22", "china": 8.61, "eu": 96.11, "south_korea": 16.80, "us_california": 32.75},
    {"date": "2022-04-25", "china": 8.61, "eu": 89.28, "south_korea": 17.44, "us_california": 32.75},
    {"date": "2022-04-26", "china": 8.61, "eu": 87.77, "south_korea": 17.44, "us_california": 32.75},
    {"date": "2022-04-27", "china": 8.47, "eu": 85.41, "south_korea": 17.44, "us_california": 32.75},
    {"date": "2022-04-28", "china": 8.47, "eu": 87.06, "south_korea": 17.44, "us_california": 30.6},
    {"date": "2022-04-29", "china": 8.44, "eu": 88.39, "south_korea": 17.44, "us_california": 30.6},
    {"date": "2022-05-02", "china": 8.44, "eu": 88.39, "south_korea": 17.44, "us_california": 30.6},
    {"date": "2022-05-03", "china": 8.44, "eu": 88.39, "south_korea": 17.44, "us_california": 30.6},
    {"date": "2022-05-04", "china": 8.44, "eu": 86.24, "south_korea": 17.44, "us_california": 30.6},
    {"date": "2022-05-05", "china": 8.44, "eu": 83.37, "south_korea": 17.44, "us_california": 30.6},
    {"date": "2022-05-06", "china": 8.44, "eu": 80.24, "south_korea": 17.44, "us_california": 30.6},
    {"date": "2022-05-09", "china": 8.44, "eu": 79.53, "south_korea": 17.44, "us_california": 30.6},
    {"date": "2022-05-10", "china": 8.44, "eu": 78.24, "south_korea": 17.44, "us_california": 30.6},
    {"date": "2022-05-11", "china": 8.44, "eu": 80.47, "south_korea": 17.44, "us_california": 30.6},
    {"date": "2022-05-12", "china": 8.44, "eu": 80.96, "south_korea": 17.44, "us_california": 30.6},
    {"date": "2022-05-13", "china": 8.44, "eu": 81.39, "south_korea": 17.44, "us_california": 30.6},
    {"date": "2022-05-16", "china": 8.44, "eu": 78.79, "south_korea": 17.44, "us_california": 30.6},
    {"date": "2022-05-17", "china": 8.44, "eu": 78.37, "south_korea": 17.44, "us_california": 30.6},
    {"date": "2022-05-18", "china": 8.44, "eu": 78.70, "south_korea": 17.44, "us_california": 30.6},
    {"date": "2022-05-19", "china": 8.44, "eu": 78.52, "south_korea": 17.44, "us_california": 30.6},
    {"date": "2022-05-20", "china": 8.44, "eu": 78.96, "south_korea": 17.44, "us_california": 30.6},
    {"date": "2022-05-23", "china": 8.44, "eu": 79.34, "south_korea": 17.44, "us_california": 30.6},
    {"date": "2022-05-24", "china": 8.44, "eu": 78.78, "south_korea": 17.44, "us_california": 30.6},
    {"date": "2022-05-25", "china": 8.44, "eu": 79.24, "south_korea": 17.44, "us_california": 30.6},
    {"date": "2022-05-26", "china": 8.44, "eu": 79.38, "south_korea": 17.44, "us_california": 30.6},
    {"date": "2022-05-27", "china": 8.44, "eu": 78.96, "south_korea": 17.44, "us_california": 30.6},
    {"date": "2022-05-30", "china": 8.44, "eu": 78.69, "south_korea": 17.44, "us_california": 30.6},
    {"date": "2022-05-31", "china": 8.44, "eu": 78.22, "south_korea": 17.44, "us_california": 30.6},
    {"date": "2022-06-01", "china": 8.44, "eu": 78.12, "south_korea": 17.44, "us_california": 30.6},
    {"date": "2022-06-02", "china": 8.44, "eu": 78.62, "south_korea": 17.44, "us_california": 30.6},
    {"date": "2022-06-03", "china": 8.44, "eu": 78.34, "south_korea": 17.44, "us_california": 30.6},
    {"date": "2022-06-06", "china": 8.44, "eu": 77.98, "south_korea": 17.44, "us_california": 30.6},
    {"date": "2022-06-07", "china": 8.44, "eu": 77.72, "south_korea": 17.44, "us_california": 30.6},
    {"date": "2022-06-08", "china": 8.44, "eu": 77.81, "south_korea": 17.44, "us_california": 30.6},
    {"date": "2022-06-09", "china": 8.44, "eu": 78.46, "south_korea": 17.44, "us_california": 30.6},
    {"date": "2022-06-10", "china": 8.44, "eu": 78.49, "south_korea": 17.44, "us_california": 30.6},
    {"date": "2022-06-13", "china": 8.44, "eu": 78.81, "south_korea": 17.44, "us_california": 30.6},
    {"date": "2022-06-14", "china": 8.44, "eu": 78.73, "south_korea": 17.44, "us_california": 30.6},
    {"date": "2022-06-15", "china": 8.44, "eu": 78.52, "south_korea": 17.44, "us_california": 30.6},
    {"date": "2022-06-16", "china": 8.44, "eu": 78.83, "south_korea": 17.44, "us_california": 30.6},
    {"date": "2022-06-17", "china": 8.44, "eu": 78.77, "south_korea": 17.44, "us_california": 30.6},
    {"date": "2022-06-20", "china": 8.44, "eu": 78.41, "south_korea": 17.44, "us_california": 30.6},
    {"date": "2022-06-21", "china": 8.44, "eu": 78.65, "south_korea": 17.44, "us_california": 30.6},
    {"date": "2022-06-22", "china": 8.44, "eu": 78.43, "south_korea": 17.44, "us_california": 30.6},
    {"date": "2022-06-23", "china": 8.44, "eu": 78.65, "south_korea": 17.44, "us_california": 30.6},
    {"date": "2022-06-24", "china": 8.44, "eu": 78.67, "south_korea": 17.44, "us_california": 30.6},
    {"date": "2022-06-27", "china": 8.44, "eu": 78.35, "south_korea": 17.44, "us_california": 30.6},
    {"date": "2022-06-28", "china": 8.44, "eu": 78.21, "south_korea": 17.44, "us_california": 30.6},
    {"date": "2022-06-29", "china": 8.44, "eu": 78.42, "south_korea": 17.44, "us_california": 30.6},
    {"date": "2022-06-30", "china": 8.44, "eu": 78.36, "south_korea": 17.44, "us_california": 30.6},
    {"date": "2022-07-01", "china": 8.44, "eu": 78.50, "south_korea": 17.44, "us_california": 30.6},
    {"date": "2022-07-05", "china": 8.44, "eu": 78.59, "south_korea": 17.44, "us_california": 30.6},
    {"date": "2022-07-06", "china": 8.44, "eu": 78.48, "south_korea": 17.44, "us_california": 30.6},
    {"date": "2022-07-07", "china": 8.44, "eu": 78.56, "south_korea": 17.44, "us_california": 30.6},
    {"date": "2022-07-08", "china": 8.44, "eu": 78.59, "south_korea": 17.44, "us_california": 30.6},
    {"date": "2022-07-11", "china": 8.44, "eu": 78.52, "south_korea": 17.44, "us_california": 30.6},
    {"date": "2022-07-12", "china": 8.44, "eu": 78.46, "south_korea": 17.44, "us_california": 30.6},
    {"date": "2022-07-13", "china": 8.44, "eu": 78.60, "south_korea": 17.44, "us_california": 30.6},
    {"date": "2022-07-14", "china": 8.44, "eu": 78.52, "south_korea": 17.44, "us_california": 30.6},
    {"date": "2022-07-15", "china": 8.44, "eu": 78.50, "south_korea": 17.44, "us_california": 30.6},
    {"date": "2022-07-18", "china": 8.44, "eu": 78.47, "south_korea": 17.44, "us_california": 30.6},
    {"date": "2022-07-19", "china": 8.44, "eu": 78.35, "south_korea": 17.44, "us_california": 30.6},
    {"date": "2022-07-20", "china": 8.44, "eu": 78.38, "south_korea": 17.44, "us_california": 30.6},
    {"date": "2022-07-21", "china": 8.44, "eu": 78.42, "south_korea": 17.44, "us_california": 30.6},
    {"date": "2022-07-22", "china": 8.44, "eu": 78.50, "south_korea": 17.44, "us_california": 30.6},
    {"date": "2022-07-25", "china": 8.44, "eu": 78.51, "south_korea": 17.44, "us_california": 30.6},
    {"date": "2022-07-26", "china": 8.44, "eu": 78.61, "south_korea": 17.44, "us_california": 30.6},
    {"date": "2022-07-27", "china": 8.44, "eu": 78.64, "south_korea": 17.44, "us_california": 30.6},
    {"date": "2022-07-28", "china": 8.44, "eu": 78.62, "south_korea": 17.44, "us_california": 30.6},
    {"date": "2022-07-29", "china": 8.44, "eu": 78.61, "south_korea": 17.44, "us_california": 30.6},
    {"date": "2022-08-01", "china": 8.44, "eu": 78.66, "south_korea": 17.44, "us_california": 30.6},
    {"date": "2022-08-02", "china": 8.44, "eu": 78.65, "south_korea": 17.44, "us_california": 30.6},
    {"date": "2022-08-03", "china": 8.44, "eu": 78.59, "south_korea": 17.44, "us_california": 30.6},
    {"date": "2022-08-04", "china": 8.44, "eu": 78.55, "south_korea": 17.44, "us_california": 30.6},
    {"date": "2022-08-05", "china": 8.44, "eu": 78.50, "south_korea": 17.44, "us_california": 30.6},
    {"date": "2022-08-08", "china": 8.44, "eu": 78.41, "south_korea": 17.44, "us_california": 30.6},
    {"date": "2022-08-09", "china": 8.44, "eu": 78.37, "south_korea": 17.44, "us_california": 30.6},
    {"date": "2022-08-10", "china": 8.44, "eu": 78.39, "south_korea": 17.44, "us_california": 30.6},
    {"date": "2022-08-11", "china": 8.44, "eu": 78.36, "south_korea": 17.44, "us_california": 30.6},
    {"date": "2022-08-12", "china": 8.44, "eu": 78.35, "south_korea": 17.44, "us_california": 30.6},
    {"date": "2022-08-15", "china": 8.44, "eu": 78.34, "south_korea": 17.44, "us_california": 30.6},
    {"date": "2022-08-16", "china": 8.44, "eu": 78.32, "south_korea": 17.44, "us_california": 30.6},
    {"date": "2022-08-17", "china": 8.44, "eu": 78.36, "south_korea": 17.44, "us_california": 30.6},
    {"date": "2022-08-18", "china": 8.44, "eu": 78.38, "south_korea": 17.44, "us_california": 30.6},
    {"date": "2022-08-19", "china": 8.44, "eu": 78.40, "south_korea": 17.44, "us_california": 30.6},
    {"date": "2022-08-22", "china": 8.44, "eu": 78.38, "south_korea": 17.44, "us_california": 30.6},
    {"date": "2022-08-23", "china": 8.44, "eu": 78.37, "south_korea": 17.44, "us_california": 30.6},
    {"date": "2022-08-24", "china": 8.44, "eu": 78.41, "south_korea": 17.44, "us_california": 30.6},
    {"date": "2022-08-25", "china": 8.44, "eu": 78.43, "south_korea": 17.44, "us_california": 30.6},
    {"date": "2022-08-26", "china": 8.44, "eu": 78.41, "south_korea": 17.44, "us_california": 30.6},
    {"date": "2022-08-29", "china": 8.44, "eu": 78.42, "south_korea": 17.44, "us_california": 30.6},
    {"date": "2022-08-30", "china": 8.44, "eu": 78.41, "south_korea": 17.44, "us_california": 30.6},
    {"date": "2022-08-31", "china": 8.44, "eu": 78.42, "south_korea": 17.44, "us_california": 30.6},
    {"date": "2022-09-01", "china": 8.44, "eu": 78.41, "south_korea": 17.44, "us_california": 30.6},
    {"date": "2022-09-02", "china": 8.44, "eu": 78.44, "south_korea": 17.44, "us_california": 30.6},
    {"date": "2022-09-05", "china": 8.44, "eu": 78.46, "south_korea": 17.44, "us_california": 30.6},
    {"date": "2022-09-06", "china": 8.44, "eu": 78.45, "south_korea": 17.44, "us_california": 30.6},
    {"date": "2022-09-07", "china": 8.44, "eu": 78.44, "south_korea": 17.44, "us_california": 30.6},
    {"date": "2022-09-08", "china": 8.44, "eu": 78.42, "south_korea": 17.44, "us_california": 30.6},
    {"date": "2022-09-09", "china": 8.44, "eu": 78.41, "south_korea": 17.44, "us_california": 30.6},
    {"date": "2022-09-12", "china": 8.44, "eu": 78.39, "south_korea": 17.44, "us_california": 30.6},
    {"date": "2022-09-13", "china": 8.44, "eu": 78.41, "south_korea": 17.44, "us_california": 30.6},
    {"date": "2022-09-14", "china": 8.44, "eu": 78.39, "south_korea": 17.44, "us_california": 30.6},
    {"date": "2022-09-15", "china": 8.44, "eu": 78.41, "south_korea": 17.44, "us_california": 30.6},
    {"date": "2022-09-16", "china": 8.44, "eu": 78.43, "south_korea": 17.44, "us_california": 30.6},
    {"date": "2022-09-19", "china": 8.44, "eu": 78.44, "south_korea": 17.44, "us_california": 30.6},
    {"date": "2022-09-20", "china": 8.44, "eu": 78.43, "south_korea": 17.44, "us_california": 30.6},
    {"date": "2022-09-21", "china": 8.44, "eu": 78.45, "south_korea": 17.44, "us_california": 30.6},
    {"date": "2022-09-22", "china": 8.44, "eu": 78.44, "south_korea": 17.44, "us_california": 30.6},
    {"date": "2022-09-23", "china": 8.44, "eu": 78.46, "south_korea": 17.44, "us_california": 30.6},
    {"date": "2022-09-26", "china": 8.44, "eu": 78.45, "south_korea": 17.44, "us_california": 30.6},
    {"date": "2022-09-27", "china": 8.44, "eu": 78.44, "south_korea": 17.44, "us_california": 30.6},
    {"date": "2022-09-28", "china": 8.44, "eu": 78.45, "south_korea": 17.44, "us_california": 30.6},
    {"date": "2022-09-29", "china": 8.44, "eu": 78.47, "south_korea": 17.44, "us_california": 30.6},
    {"date": "2022-09-30", "china": 8.44, "eu": 78.45, "south_korea": 17.44, "us_california": 30.6},
    {"date": "2022-10-03", "china": 8.44, "eu": 78.46, "south_korea": 17.44, "us_california": 30.6},
    {"date": "2022-10-04", "china": 8.44, "eu": 78.45, "south_korea": 17.44, "us_california": 30.6},
    {"date": "2022-10-05", "china": 8.44, "eu": 78.44, "south_korea": 17.44, "us_california": 30.6},
    {"date": "2022-10-06", "china": 8.44, "eu": 78.43, "south_korea": 17.44, "us_california": 30.6},
    {"date": "2022-10-07", "china": 8.44, "eu": 78.44, "south_korea": 17.44, "us_california": 30.6},
    {"date": "2022-10-11", "china": 8.44, "eu": 78.46, "south_korea": 17.44, "us_california": 30.6},
    {"date": "2022-10-12", "china": 8.44, "eu": 78.45, "south_korea": 17.44, "us_california": 30.6},
    {"date": "2022-10-13", "china": 8.44, "eu": 78.46, "south_korea": 17.44, "us_california": 30.6},
    {"date": "2022-10-14", "china": 8.44, "eu": 78.47, "south_korea": 17.44, "us_california": 30.6},
    {"date": "2022-10-17", "china": 8.44, "eu": 78.48, "south_korea": 17.44, "us_california": 30.6},
    {"date": "2022-10-18", "china": 8.44, "eu": 78.47, "south_korea": 17.44, "us_california": 30.6},
    {"date": "2022-10-19", "china": 8.44, "eu": 78.48, "south_korea": 17.44, "us_california": 30.6},
    {"date": "2022-10-20", "china": 8.44, "eu": 78.47, "south_korea": 17.44, "us_california": 30.6},
    {"date": "2022-10-21", "china": 8.44, "eu": 78.49, "south_korea": 17.44, "us_california": 30.6},
    {"date": "2022-10-24", "china": 8.44, "eu": 78.50, "south_korea": 17.44, "us_california": 30.6},
    {"date": "2022-10-25", "china": 8.44, "eu": 78.49, "south_korea": 17.44, "us_california": 30.6},
    {"date": "2022-10-26", "china": 8.44, "eu": 78.51, "south_korea": 17.44, "us_california": 30.6},
    {"date": "2022-10-27", "china": 8.44, "eu": 78.50, "south_korea": 17.44, "us_california": 30.6},
    {"date": "2022-10-28", "china": 8.44, "eu": 78.51, "south_korea": 17.44, "us_california": 30.6},
    {"date": "2022-10-31", "china": 8.44, "eu": 78.53, "south_korea": 17.44, "us_california": 30.6},
    {"date": "2022-11-01", "china": 8.44, "eu": 78.52, "south_korea": 17.44, "us_california": 30.6},
    {"date": "2022-11-02", "china": 8.44, "eu": 78.53, "south_korea": 17.44, "us_california": 30.6},
    {"date": "2022-11-03", "china": 8.44, "eu": 78.54, "south_korea": 17.44, "us_california": 30.6},
    {"date": "2022-11-04", "china": 8.44, "eu": 78.53, "south_korea": 17.44, "us_california": 30.6},
    {"date": "2022-11-07", "china": 8.44, "eu": 78.52, "south_korea": 17.44, "us_california": 30.6},
    {"date": "2022-11-08", "china": 8.44, "eu": 78.50, "south_korea": 17.44, "us_california": 30.6},
    {"date": "2022-11-09", "china": 8.44, "eu": 78.52, "south_korea": 17.44, "us_california": 30.6},
    {"date": "2022-11-10", "china": 8.44, "eu": 78.53, "south_korea": 17.44, "us_california": 30.6},
    {"date": "2022-11-11", "china": 8.44, "eu": 78.54, "south_korea": 17.44, "us_california": 30.6},
    {"date": "2022-11-14", "china": 8.44, "eu": 78.53, "south_korea": 17.44, "us_california": 30.6},
    {"date": "2022-11-15", "china": 8.44, "eu": 78.55, "south_korea": 17.44, "us_california": 30.6},
    {"date": "2022-11-16", "china": 8.44, "eu": 78.57, "south_korea": 17.44, "us_california": 30.6},
    {"date": "2022-11-17", "china": 8.44, "eu": 78.56, "south_korea": 17.44, "us_california": 30.6},
    {"date": "2022-11-18", "china": 8.44, "eu": 78.54, "south_korea": 17.44, "us_california": 30.6},
    {"date": "2022-11-21", "china": 8.44, "eu": 78.53, "south_korea": 17.44, "us_california": 30.6},
    {"date": "2022-11-22", "china": 8.44, "eu": 78.54, "south_korea": 17.44, "us_california": 30.6},
    {"date": "2022-11-23", "china": 8.44, "eu": 78.53, "south_korea": 17.44, "us_california": 30.6},
    {"date": "2022-11-25", "china": 8.44, "eu": 78.52, "south_korea": 17.44, "us_california": 30.6},
    {"date": "2022-11-28", "china": 8.44, "eu": 78.51, "south_korea": 17.44, "us_california": 30.6},
    {"date": "2022-11-29", "china": 8.44, "eu": 78.52, "south_korea": 17.44, "us_california": 30.6},
    {"date": "2022-11-30", "china": 8.44, "eu": 78.50, "south_korea": 17.44, "us_california": 30.6},
    {"date": "2022-12-01", "china": 8.44, "eu": 78.52, "south_korea": 17.44, "us_california": 30.6},
    {"date": "2022-12-02", "china": 8.44, "eu": 78.53, "south_korea": 17.44, "us_california": 30.6},
    {"date": "2022-12-05", "china": 8.44, "eu": 78.52, "south_korea": 17.44, "us_california": 30.6},
    {"date": "2022-12-06", "china": 8.44, "eu": 78.54, "south_korea": 17.44, "us_california": 30.6},
    {"date": "2022-12-07", "china": 8.44, "eu": 78.55, "south_korea": 17.44, "us_california": 30.6},
    {"date": "2022-12-08", "china": 8.44, "eu": 78.56, "south_korea": 17.44, "us_california": 30.6},
    {"date": "2022-12-09", "china": 8.44, "eu": 78.55, "south_korea": 17.44, "us_california": 30.6},
    {"date": "2022-12-12", "china": 8.44, "eu": 78.54, "south_korea": 17.44, "us_california": 30.6},
    {"date": "2022-12-13", "china": 8.44, "eu": 78.56, "south_korea": 17.44, "us_california": 30.6},
    {"date": "2022-12-14", "china": 8.44, "eu": 78.57, "south_korea": 17.44, "us_california": 30.6},
    {"date": "2022-12-15", "china": 8.44, "eu": 78.56, "south_korea": 17.44, "us_california": 30.6},
    {"date": "2022-12-16", "china": 8.44, "eu": 78.58, "south_korea": 17.44, "us_california": 30.6},
    {"date": "2022-12-19", "china": 8.44, "eu": 78.59, "south_korea": 17.44, "us_california": 30.6},
    {"date": "2022-12-20", "china": 8.44, "eu": 78.60, "south_korea": 17.44, "us_california": 30.6},
    {"date": "2022-12-21", "china": 8.44, "eu": 78.62, "south_korea": 17.44, "us_california": 30.6},
    {"date": "2022-12-22", "china": 8.44, "eu": 78.61, "south_korea": 17.44, "us_california": 30.6},
    {"date": "2022-12-23", "china": 8.44, "eu": 78.63, "south_korea": 17.44, "us_california": 30.6},
    {"date": "2022-12-27", "china": 8.44, "eu": 78.62, "south_korea": 17.44, "us_california": 30.6},
    {"date": "2022-12-28", "china": 8.44, "eu": 78.63, "south_korea": 17.44, "us_california": 30.6},
    {"date": "2022-12-29", "china": 8.44, "eu": 78.64, "south_korea": 17.44, "us_california": 30.6},
    {"date": "2022-12-30", "china": 8.44, "eu": 78.66, "south_korea": 17.44, "us_california": 30.6}
]